relatable/__imports.py
relatable/__init__.py
relatable/relarow.py
relatable/relatable.py
talamus_relatable-1.0.2.dist-info/LICENSE
talamus_relatable-1.0.2.dist-info/WHEEL
talamus_relatable-1.0.2.dist-info/METADATA
talamus_relatable-1.0.2.dist-info/RECORD
