Metadata-Version: 2.1
Name: talamus-relatable
Version: 1.0.2
Summary: A relational database -like table of rows.
Home-page: https://github.com/talamus/python-relatable
License: MIT
Author: Tero Niemi
Author-email: talamus@gmail.com
Requires-Python: >=3.10,<4.0
Classifier: License :: OSI Approved :: MIT License
Classifier: Programming Language :: Python :: 3
Classifier: Programming Language :: Python :: 3.10
Classifier: Programming Language :: Python :: 3.11
Classifier: Topic :: Software Development :: Libraries :: Python Modules
Project-URL: Repository, https://github.com/talamus/python-relatable
